gidconfig/__init__.py
gidconfig/custom_config/__init__.py
gidconfig/custom_config/custom_syntax_config.py
gidconfig/data/__init__.py
gidconfig/data/enums.py
gidconfig/experimental/__init__.py
gidconfig/experimental/experimental_abstract.py
gidconfig/experimental/experimental_ini.py
gidconfig/experimental/experimental_json.py
gidconfig/experimental/experimental_strategy.py
gidconfig/standard/__init__.py
gidconfig/standard/classes.py
gidconfig/standard/factories.py
gidconfig/standard/functions.py
gidconfig/utility/__init__.py
gidconfig/utility/decorators.py
gidconfig/utility/functions.py
gidconfig-0.2.17.dist-info/LICENSE
gidconfig-0.2.17.dist-info/WHEEL
gidconfig-0.2.17.dist-info/METADATA
gidconfig-0.2.17.dist-info/RECORD
